sparkplug_feature_flags/__init__.py
sparkplug_feature_flags/apps.py
sparkplug_feature_flags/enums/__init__.py
sparkplug_feature_flags/enums/client.py
sparkplug_feature_flags/factories.py
sparkplug_feature_flags/fields/__init__.py
sparkplug_feature_flags/fields/feature_flag.py
sparkplug_feature_flags/fields/flag_access.py
sparkplug_feature_flags/management/__init__.py
sparkplug_feature_flags/management/commands/__init__.py
sparkplug_feature_flags/management/commands/seed_flag_access.py
sparkplug_feature_flags/management/commands/sync_feature_flags.py
sparkplug_feature_flags/migrations/0001_initial.py
sparkplug_feature_flags/migrations/0002_featureflag_feature_flag_title_trgm.py
sparkplug_feature_flags/migrations/0003_alter_featureflag_created_alter_featureflag_modified_and_more.py
sparkplug_feature_flags/migrations/__init__.py
sparkplug_feature_flags/models/__init__.py
sparkplug_feature_flags/models/feature_flag.py
sparkplug_feature_flags/models/flag_access.py
sparkplug_feature_flags/queries/__init__.py
sparkplug_feature_flags/queries/feature_flag_autocomplete.py
sparkplug_feature_flags/queries/feature_flag_list.py
sparkplug_feature_flags/queries/feature_flag_search.py
sparkplug_feature_flags/queries/flag_access_list.py
sparkplug_feature_flags/serializers/__init__.py
sparkplug_feature_flags/serializers/feature_flag.py
sparkplug_feature_flags/serializers/flag_access.py
sparkplug_feature_flags/serializers/user_uuid.py
sparkplug_feature_flags/tests/__init__.py
sparkplug_feature_flags/tests/queries/__init__.py
sparkplug_feature_flags/tests/queries/test_feature_flag_autocomplete.py
sparkplug_feature_flags/tests/queries/test_feature_flag_list.py
sparkplug_feature_flags/tests/queries/test_feature_flag_search.py
sparkplug_feature_flags/tests/queries/test_flag_access_list.py
sparkplug_feature_flags/tests/serializers/__init__.py
sparkplug_feature_flags/tests/serializers/test_user_uuid.py
sparkplug_feature_flags/tests/views/__init__.py
sparkplug_api_feature_flags-1.1.3.dist-info/METADATA
sparkplug_api_feature_flags-1.1.3.dist-info/WHEEL
sparkplug_api_feature_flags-1.1.3.dist-info/RECORD
