Metadata-Version: 2.3
Name: sparkplug-api-feature-flags
Version: 1.1.3
Summary: Feature flag package for sparkplug apps
License: MIT
Author: Sparkplug Marcus
Author-email: sparkplugmarcus@gmail.com
Requires-Python: >=3.11,<4.0
Classifier: License :: OSI Approved :: MIT License
Classifier: Programming Language :: Python :: 3
Classifier: Programming Language :: Python :: 3.11
Classifier: Programming Language :: Python :: 3.12
Classifier: Programming Language :: Python :: 3.13
Requires-Dist: sparkplug-api-core (>=1.1.5,<1.2.0)
